login_history_too/__init__.py
login_history_too/admin.py
login_history_too/apps.py
login_history_too/mixins.py
login_history_too/models.py
login_history_too/settings.py
login_history_too/signals.py
login_history_too/utils.py
login_history_too/helpers/__init__.py
login_history_too/helpers/ip.py
login_history_too/helpers/ua.py
login_history_too/helpers/tests/__init__.py
login_history_too/helpers/tests/test_ip.py
login_history_too/helpers/tests/test_ua.py
login_history_too/migrations/0001_initial.py
login_history_too/migrations/__init__.py
login_history_too/static/login_history_too/css/.gitkeep
login_history_too/static/login_history_too/img/.gitkeep
login_history_too/static/login_history_too/js/.gitkeep
login_history_too/static/login_history_too/js/logins.js
login_history_too/static/login_history_too/js/ace-builds/ace.js
login_history_too/static/login_history_too/js/ace-builds/ext-beautify.js
login_history_too/static/login_history_too/js/ace-builds/ext-code_lens.js
login_history_too/static/login_history_too/js/ace-builds/ext-elastic_tabstops_lite.js
login_history_too/static/login_history_too/js/ace-builds/ext-emmet.js
login_history_too/static/login_history_too/js/ace-builds/ext-error_marker.js
login_history_too/static/login_history_too/js/ace-builds/ext-keybinding_menu.js
login_history_too/static/login_history_too/js/ace-builds/ext-language_tools.js
login_history_too/static/login_history_too/js/ace-builds/ext-linking.js
login_history_too/static/login_history_too/js/ace-builds/ext-modelist.js
login_history_too/static/login_history_too/js/ace-builds/ext-options.js
login_history_too/static/login_history_too/js/ace-builds/ext-prompt.js
login_history_too/static/login_history_too/js/ace-builds/ext-rtl.js
login_history_too/static/login_history_too/js/ace-builds/ext-searchbox.js
login_history_too/static/login_history_too/js/ace-builds/ext-settings_menu.js
login_history_too/static/login_history_too/js/ace-builds/ext-spellcheck.js
login_history_too-0.1.1.dist-info/licenses/AUTHORS.md
login_history_too-0.1.1.dist-info/licenses/LICENSE
login_history_too-0.1.1.dist-info/METADATA
login_history_too-0.1.1.dist-info/WHEEL
login_history_too-0.1.1.dist-info/top_level.txt
login_history_too-0.1.1.dist-info/RECORD
