Metadata-Version: 2.4
Name: login-history-too
Version: 0.1.1
Summary: It's easy to use, plug-in django app that once included, stores logins history (with device data, like IP, user-agent, location etc.) of all users.
Author-email: Tim Santor <tsantor@xstudios.com>
Project-URL: Repository, https://github.com/tsantor/login-history-too.git
Project-URL: Issues, https://github.com/tsantor/login-history-too/issues
Project-URL: Changelog, https://github.com/tsantor/login-history-too/blob/master/HISTORY.md
Classifier: Development Status :: 5 - Production/Stable
Classifier: Intended Audience :: Developers
Classifier: Natural Language :: English
Classifier: Programming Language :: Python :: 3.8
Classifier: Programming Language :: Python :: 3.9
Classifier: Programming Language :: Python :: 3.10
Classifier: Programming Language :: Python :: 3.11
Classifier: Programming Language :: Python :: 3.12
Classifier: Programming Language :: Python :: 3.13
Requires-Python: >=3.8
License-File: LICENSE
License-File: AUTHORS.md
Requires-Dist: django-ipware>=7.0.1
Requires-Dist: requests>=2.32.3
Requires-Dist: user-agents>=2.2.0
Provides-Extra: dev
Dynamic: license-file
